{
    "id": 4593033117738,
    "title": "The Kenzie Top \/ Black",
    "body_html": "\u003cp class=\"stock-notification\"\u003e\u003cspan data-mce-fragment=\"1\"\u003eShop matching \u003cspan style=\"text-decoration: underline;\"\u003e\u003ca href=\"https:\/\/shop437.com\/products\/the-kenzie-bottoms-black\"\u003eKenzie Bottoms\u003c\/a\u003e\u003ca href=\"https:\/\/shop437.com\/products\/the-aubrey-bottoms-medium-coverage-black\"\u003e\u00a0\u003c\/a\u003e\u003c\/span\u003e\u003c\/span\u003e\u003c\/p\u003e\n\u003ch4 data-mce-fragment=\"1\"\u003e\u003cb data-mce-fragment=\"1\"\u003e Features\u003c\/b\u003e\u003c\/h4\u003e\n\u003cul\u003e\n\u003cli\u003eCan be worn over 12+ ways as seen \u003cspan style=\"text-decoration: underline;\"\u003e\u003ca href=\"https:\/\/www.instagram.com\/p\/Bkgc62Fhr7M\/?taken-by=437swimwear\"\u003ehere\u003c\/a\u003e \u003c\/span\u003e\n\u003c\/li\u003e\n\u003cli\u003eCurve-hugging, double layered fabric with a seamless finish\u003c\/li\u003e\n\u003cli\u003eAdjustable tie-front allows for more or less coverage\u003c\/li\u003e\n\u003c\/ul\u003e\n\u003cul\u003e\u003c\/ul\u003e\n\u003cb data-mce-fragment=\"1\"\u003e \u003c\/b\u003e\n",
    "vendor": "437 SWIMWEAR",
    "product_type": "Kenzie Top",
    "created_at": "2020-10-05T10:29:47-04:00",
    "handle": "the-kenzie-top-black",
    "updated_at": "2022-02-27T02:10:31-05:00",
    "published_at": "2020-10-05T10:35:53-04:00",
    "template_suffix": "v5",
    "published_scope": "global",
    "tags": "BLACK, C_FABRICS_CLASSIC, C_TYPES_TOPS, cta-addtocart, KENZIE, LARGE, MEDIUM, pdp_status_selling_fast, PROMO, SHOWTOP, SMALL, SOLID, SOLIDS, STAPLE, SWIMWEAR, TOPS, VERSATILE, WRAP, X LARGE, X SMALL",
    "variants": [
      {
        "id": 32042793992234,
        "product_id": 4593033117738,
        "title": "X SMALL",
        "price": "85.00",
        "sku": "KE-TBXS",
        "position": 1,
        "compare_at_price": "",
        "fulfillment_service": "manual",
        "inventory_management": "shopify",
        "option1": "X SMALL",
        "option2": null,
        "option3": null,
        "created_at": "2020-10-05T10:29:47-04:00",
        "updated_at": "2022-02-26T21:38:03-05:00",
        "taxable": true,
        "barcode": "93992234",
        "grams": 72,
        "image_id": null,
        "weight": 72.0,
        "weight_unit": "g",
        "tax_code": "",
        "requires_shipping": true
      },
      {
        "id": 32042794025002,
        "product_id": 4593033117738,
        "title": "SMALL",
        "price": "85.00",
        "sku": "KE-TBSS",
        "position": 2,
        "compare_at_price": "",
        "fulfillment_service": "manual",
        "inventory_management": "shopify",
        "option1": "SMALL",
        "option2": null,
        "option3": null,
        "created_at": "2020-10-05T10:29:47-04:00",
        "updated_at": "2022-02-26T05:59:55-05:00",
        "taxable": true,
        "barcode": "94025002",
        "grams": 72,
        "image_id": null,
        "weight": 72.0,
        "weight_unit": "g",
        "tax_code": "",
        "requires_shipping": true
      },
      {
        "id": 32042794057770,
        "product_id": 4593033117738,
        "title": "MEDIUM",
        "price": "85.00",
        "sku": "KE-TBMM",
        "position": 3,
        "compare_at_price": "",
        "fulfillment_service": "manual",
        "inventory_management": "shopify",
        "option1": "MEDIUM",
        "option2": null,
        "option3": null,
        "created_at": "2020-10-05T10:29:47-04:00",
        "updated_at": "2022-02-27T02:09:32-05:00",
        "taxable": true,
        "barcode": "94057770",
        "grams": 72,
        "image_id": null,
        "weight": 72.0,
        "weight_unit": "g",
        "tax_code": "",
        "requires_shipping": true
      },
      {
        "id": 32042794090538,
        "product_id": 4593033117738,
        "title": "LARGE",
        "price": "85.00",
        "sku": "KE-TBLL",
        "position": 4,
        "compare_at_price": "",
        "fulfillment_service": "manual",
        "inventory_management": "shopify",
        "option1": "LARGE",
        "option2": null,
        "option3": null,
        "created_at": "2020-10-05T10:29:47-04:00",
        "updated_at": "2022-02-24T19:42:06-05:00",
        "taxable": true,
        "barcode": "94090538",
        "grams": 72,
        "image_id": null,
        "weight": 72.0,
        "weight_unit": "g",
        "tax_code": "",
        "requires_shipping": true
      },
      {
        "id": 32042794123306,
        "product_id": 4593033117738,
        "title": "X LARGE",
        "price": "85.00",
        "sku": "KE-TBXL",
        "position": 5,
        "compare_at_price": "",
        "fulfillment_service": "manual",
        "inventory_management": "shopify",
        "option1": "X LARGE",
        "option2": null,
        "option3": null,
        "created_at": "2020-10-05T10:29:47-04:00",
        "updated_at": "2022-02-25T20:29:01-05:00",
        "taxable": true,
        "barcode": "94123306",
        "grams": 72,
        "image_id": null,
        "weight": 72.0,
        "weight_unit": "g",
        "tax_code": "",
        "requires_shipping": true
      },
      {
        "id": 32199799963690,
        "product_id": 4593033117738,
        "title": "XX LARGE",
        "price": "85.00",
        "sku": "KE-TBXXL",
        "position": 6,
        "compare_at_price": "",
        "fulfillment_service": "manual",
        "inventory_management": "shopify",
        "option1": "XX LARGE",
        "option2": null,
        "option3": null,
        "created_at": "2020-12-02T10:07:20-05:00",
        "updated_at": "2022-02-22T10:50:39-05:00",
        "taxable": true,
        "barcode": "99963690",
        "grams": 72,
        "image_id": null,
        "weight": 72.0,
        "weight_unit": "g",
        "tax_code": "",
        "requires_shipping": true
      }
    ],
    "options": [
      {
        "id": 6003682934826,
        "product_id": 4593033117738,
        "name": "Size",
        "position": 1,
        "values": [
          "X SMALL",
          "SMALL",
          "MEDIUM",
          "LARGE",
          "X LARGE",
          "XX LARGE"
        ]
      }
    ],
    "images": [
      {
        "id": 28759888429098,
        "product_id": 4593033117738,
        "media_type": "image",
        "position": 1,
        "created_at": "2021-11-18T16:08:56-05:00",
        "updated_at": "2021-11-18T16:08:59-05:00",
        "alt": null,
        "width": 1250,
        "height": 1667,
        "src": "https:\/\/cdn.shopify.com\/s\/files\/1\/2112\/6981\/products\/JAYDAHALES.png?v=1637269739",
        "variant_ids": [
          
        ]
      },
      {
        "id": 28749179846698,
        "product_id": 4593033117738,
        "media_type": "image",
        "position": 2,
        "created_at": "2021-11-15T19:19:31-05:00",
        "updated_at": "2021-11-18T16:08:59-05:00",
        "alt": null,
        "width": 1250,
        "height": 1667,
        "src": "https:\/\/cdn.shopify.com\/s\/files\/1\/2112\/6981\/products\/DIANAMCGREGOR.png?v=1637269739",
        "variant_ids": [
          
        ]
      },
      {
        "id": 28139837980714,
        "product_id": 4593033117738,
        "media_type": "image",
        "position": 3,
        "created_at": "2021-04-23T15:43:29-04:00",
        "updated_at": "2021-11-18T16:08:59-05:00",
        "alt": null,
        "width": 1500,
        "height": 2000,
        "src": "https:\/\/cdn.shopify.com\/s\/files\/1\/2112\/6981\/products\/DSC_5511.jpg?v=1637269739",
        "variant_ids": [
          
        ]
      },
      {
        "id": 28139837620266,
        "product_id": 4593033117738,
        "media_type": "image",
        "position": 4,
        "created_at": "2021-04-23T15:43:10-04:00",
        "updated_at": "2021-11-18T16:08:59-05:00",
        "alt": null,
        "width": 3125,
        "height": 4167,
        "src": "https:\/\/cdn.shopify.com\/s\/files\/1\/2112\/6981\/products\/KenzieBlack_Versatility_34Ratio2.png?v=1637269739",
        "variant_ids": [
          
        ]
      }
    ],
    "image": {
      "id": 28759888429098,
      "product_id": 4593033117738,
      "media_type": "image",
      "position": 1,
      "created_at": "2021-11-18T16:08:56-05:00",
      "updated_at": "2021-11-18T16:08:59-05:00",
      "alt": null,
      "width": 1250,
      "height": 1667,
      "src": "https:\/\/cdn.shopify.com\/s\/files\/1\/2112\/6981\/products\/JAYDAHALES.png?v=1637269739",
      "variant_ids": [
        
      ]
    }
  }